yuanqi_plugin_mcp/__init__.py
yuanqi_plugin_mcp/__main__.py
yuanqi_plugin_mcp/server.py
hunyuan_search-0.0.3.dist-info/METADATA
hunyuan_search-0.0.3.dist-info/WHEEL
hunyuan_search-0.0.3.dist-info/entry_points.txt
hunyuan_search-0.0.3.dist-info/RECORD
